<?xml version='1.0' encoding='utf-8'?>
<Gesture Name="delete" Subject="1" Speed="unknown" Number="8" NumPts="64" Milliseconds="0" AppName="GestureRecognizer" AppVer="1.0" Date="Tuesday, June 24, 2025" TimeOfDay="09:50:26 PM"><Point X="-125.81027457853492" Y="0.0" T="0" /><Point X="-113.38259843269972" Y="-0.9295609150332922" T="0" /><Point X="-100.95406586881161" Y="-0.2369094806599179" T="0" /><Point X="-88.56304979176377" Y="1.0695414718408074" T="0" /><Point X="-76.330323565221" Y="3.3385617915971153" T="0" /><Point X="-64.19865193418788" Y="6.173167524271918" T="0" /><Point X="-52.04032261785558" Y="8.884894183430035" T="0" /><Point X="-39.81482274584391" Y="11.288509296853533" T="0" /><Point X="-27.571153040114723" Y="13.599036502240025" T="0" /><Point X="-15.366531072238573" Y="16.10589230549374" T="0" /><Point X="-3.188021249256522" Y="18.734926810623506" T="0" /><Point X="9.025351266299225" Y="21.19816069190992" T="0" /><Point X="21.214437162907103" Y="23.77662299916645" T="0" /><Point X="33.35419201431634" Y="26.57364814005598" T="0" /><Point X="45.4451266475881" Y="29.57351516894593" T="0" /><Point X="57.5309915786454" Y="32.59245866657511" T="0" /><Point X="69.6751194315699" Y="35.37088803524307" T="0" /><Point X="81.87667510264743" Y="37.892374651305175" T="0" /><Point X="94.08921388870468" Y="40.36090187383056" T="0" /><Point X="106.42713676657021" Y="42.10133564441577" T="0" /><Point X="118.85584537711628" Y="42.911680512247244" T="0" /><Point X="124.18972542146508" Y="37.13747431743508" T="0" /><Point X="114.38597251712432" Y="29.49585590834772" T="0" /><Point X="104.43023215626468" Y="22.04949518603351" T="0" /><Point X="94.47449179540504" Y="14.603134463719357" T="0" /><Point X="84.51875143454538" Y="7.156773741405203" T="0" /><Point X="74.54778327928707" Y="-0.269085551075932" T="0" /><Point X="64.44171020030888" Y="-7.512851645004602" T="0" /><Point X="54.27373357869365" Y="-14.670707634298964" T="0" /><Point X="44.1059354184471" Y="-21.82880959545882" T="0" /><Point X="34.052462218206415" Y="-29.144484727205054" T="0" /><Point X="24.093854415739514" Y="-36.5870111876454" T="0" /><Point X="14.13811405487985" Y="-44.033371909959584" T="0" /><Point X="4.182373694020242" Y="-51.47973263227374" T="0" /><Point X="-5.773366666839436" Y="-58.92609335458792" T="0" /><Point X="-15.729107027699072" Y="-66.37245407690207" T="0" /><Point X="-25.684847388558723" Y="-73.81881479921626" T="0" /><Point X="-35.640587749418344" Y="-81.26517552153044" T="0" /><Point X="-45.59632811027801" Y="-88.7115362438446" T="0" /><Point X="-55.552068471137645" Y="-96.15789696615877" T="0" /><Point X="-65.5078088319973" Y="-103.60425768847296" T="0" /><Point X="-75.81793573262038" Y="-110.54672357571604" T="0" /><Point X="-72.86004520791741" Y="-101.881963117065" T="0" /><Point X="-67.03575288688074" Y="-90.94015487407567" T="0" /><Point X="-61.8040918534612" Y="-79.71546075736185" T="0" /><Point X="-55.507015977012756" Y="-69.04556573627508" T="0" /><Point X="-50.301700230501666" Y="-57.799203314345746" T="0" /><Point X="-44.97502647890485" Y="-46.62075317378015" T="0" /><Point X="-39.12894923330434" Y="-35.69080448517863" T="0" /><Point X="-33.57678321720326" Y="-24.608664582940847" T="0" /><Point X="-28.04089171562954" Y="-13.518404253101778" T="0" /><Point X="-22.82024166336886" Y="-2.2820968521216827" T="0" /><Point X="-17.9669593741947" Y="9.118752827713337" T="0" /><Point X="-13.567545466968966" Y="20.698546899224368" T="0" /><Point X="-9.138098880747705" Y="32.26880186435133" T="0" /><Point X="-4.940870344898258" Y="43.92393137059349" T="0" /><Point X="-1.0230193642638028" Y="55.674851387744894" T="0" /><Point X="2.6743513505225565" Y="67.49391427997924" T="0" /><Point X="5.870530908947671" Y="79.45702996347882" T="0" /><Point X="9.080089901532688" Y="91.41499947299383" T="0" /><Point X="11.833890387462304" Y="103.47038686169489" T="0" /><Point X="14.459377804145618" Y="115.56772893696228" T="0" /><Point X="17.087603034765976" Y="127.66747847528373" T="0" /><Point X="20.873783962206602" Y="139.45327642428396" T="0" /></Gesture>