<?xml version='1.0' encoding='utf-8'?>
<Gesture Name="leviosa" Subject="1" Speed="unknown" Number="8" NumPts="64" Milliseconds="0" AppName="GestureRecognizer" AppVer="1.0" Date="Wednesday, June 25, 2025" TimeOfDay="09:57:54 PM"><Point X="-126.59747460343121" Y="0.0" T="0" /><Point X="-121.31873622780277" Y="-8.098432914766008" T="0" /><Point X="-116.03999785217434" Y="-16.19686582953203" T="0" /><Point X="-110.76125947654586" Y="-24.29529874429805" T="0" /><Point X="-104.6962589760613" Y="-31.309003564664053" T="0" /><Point X="-98.59311750277749" Y="-38.26030165656174" T="0" /><Point X="-92.15221464320422" Y="-44.62867872615023" T="0" /><Point X="-85.82378356909172" Y="-51.12433156993937" T="0" /><Point X="-78.8020036240369" Y="-55.835099653489195" T="0" /><Point X="-70.90765620518741" Y="-57.345529973547414" T="0" /><Point X="-63.03736220899236" Y="-58.41639208046735" T="0" /><Point X="-55.08517215043399" Y="-57.62673441556768" T="0" /><Point X="-47.20954595463746" Y="-56.10031771587245" T="0" /><Point X="-39.605690377605825" Y="-52.94506366061343" T="0" /><Point X="-32.624987565401824" Y="-47.799222988429065" T="0" /><Point X="-25.814948911321963" Y="-42.26294793872589" T="0" /><Point X="-19.37364541924906" Y="-36.17669483974805" T="0" /><Point X="-13.396819068796361" Y="-29.024151649934595" T="0" /><Point X="-8.62769522067542" Y="-21.071747162687913" T="0" /><Point X="-6.5227546901703874" Y="-10.758762522493697" T="0" /><Point X="-5.973762481233635" Y="-0.021883090632101698" T="0" /><Point X="-6.011164634055447" Y="10.74126478560487" T="0" /><Point X="-6.102109017094051" Y="21.35782058889245" T="0" /><Point X="-6.251757065679897" Y="32.1433076577367" T="0" /><Point X="-8.023922083595295" Y="42.677896607380916" T="0" /><Point X="-9.796087101510736" Y="53.21248555702516" T="0" /><Point X="-11.486007595492339" Y="63.77171233877297" T="0" /><Point X="-13.344682108139509" Y="74.26427372687587" T="0" /><Point X="-16.201661329151847" Y="84.34097378601581" T="0" /><Point X="-19.44917155846443" Y="94.20645107574532" T="0" /><Point X="-22.839681369314505" Y="103.81464395947268" T="0" /><Point X="-27.23582067195754" Y="112.67071542098032" T="0" /><Point X="-31.08329957315675" Y="122.0069203726122" T="0" /><Point X="-29.165887448866442" Y="120.50907095070065" T="0" /><Point X="-23.465196299561143" Y="113.00646492028199" T="0" /><Point X="-18.118371388742858" Y="105.0041749642993" T="0" /><Point X="-12.839633013114423" Y="96.90574204953336" T="0" /><Point X="-7.560894637485987" Y="88.80730913476725" T="0" /><Point X="-2.2821562618575086" Y="80.70887622000126" T="0" /><Point X="2.9965821137709554" Y="72.61044330523521" T="0" /><Point X="8.275320489399377" Y="64.51201039046916" T="0" /><Point X="13.554058865027798" Y="56.41357747570319" T="0" /><Point X="18.832797240656276" Y="48.315144560937114" T="0" /><Point X="24.111535616284726" Y="40.21671164617109" T="0" /><Point X="29.390273991913148" Y="32.1182787314051" T="0" /><Point X="34.6690123675416" Y="24.019845816639048" T="0" /><Point X="39.94775074317002" Y="15.921412901873055" T="0" /><Point X="44.995618538767104" Y="7.58160673146196" T="0" /><Point X="49.43813169228025" Y="-1.3910926415381226" T="0" /><Point X="54.252816728217425" Y="-10.002616854713764" T="0" /><Point X="58.77281510904436" Y="-18.89707015456962" T="0" /><Point X="63.39277162075865" Y="-27.692398294663533" T="0" /><Point X="68.31142953569253" Y="-36.1968681345524" T="0" /><Point X="73.56808751698642" Y="-44.320199527296964" T="0" /><Point X="77.921887659134" Y="-53.35346197954429" T="0" /><Point X="82.99090704477217" Y="-61.6638566224744" T="0" /><Point X="88.26964542040054" Y="-69.76228953724042" T="0" /><Point X="93.54838379602904" Y="-77.86072245200644" T="0" /><Point X="98.82712217165749" Y="-85.95915536677245" T="0" /><Point X="104.10586054728591" Y="-94.05758828153847" T="0" /><Point X="108.74568676305924" Y="-102.61959616346891" T="0" /><Point X="113.51767928561634" Y="-111.15098166813064" T="0" /><Point X="118.38368963203772" Y="-119.64069767257548" T="0" /><Point X="123.40252539656879" Y="-127.9930796273878" T="0" /></Gesture>